steeve.py
steeve-0.2.dist-info/top_level.txt
steeve-0.2.dist-info/METADATA
steeve-0.2.dist-info/DESCRIPTION.rst
steeve-0.2.dist-info/entry_points.txt
steeve-0.2.dist-info/RECORD
steeve-0.2.dist-info/WHEEL
steeve-0.2.dist-info/metadata.json
