Metadata-Version: 2.0
Name: steeve
Version: 0.2
Summary: Tiny GNU Stow–based package manager
Home-page: https://github.com/Perlence/steeve
Author: Sviatoslav Abakumov
Author-email: dust.harvesting@gmail.com
License: UNKNOWN
Download-URL: https://github.com/Perlence/steeve/archive/master.zip
Platform: UNKNOWN
Classifier: Development Status :: 4 - Beta
Classifier: Environment :: Console
Classifier: License :: OSI Approved :: BSD License
Classifier: Operating System :: POSIX :: Linux
Classifier: Programming Language :: Python :: 2
Classifier: Programming Language :: Python :: 2.7
Classifier: Topic :: System :: Installation/Setup
Classifier: Topic :: System :: Systems Administration
Classifier: Topic :: Utilities
Requires-Dist: click (>=5,<6)
Requires-Dist: whichcraft
